pynga/__init__.py
pynga/__version__.py
pynga/default_config.py
pynga/forum.py
pynga/misc.py
pynga/post.py
pynga/session.py
pynga/thread.py
pynga/user.py
pynga-2.1.4.dist-info/METADATA
pynga-2.1.4.dist-info/RECORD
pynga-2.1.4.dist-info/WHEEL
pynga-2.1.4.dist-info/top_level.txt
