Metadata-Version: 2.1
Name: pynga
Version: 2.1.4
Summary: Python implementation of NGA
Home-page: http://github.com/icyblade/pynga
Author: Icyblade Dai
Author-email: icyblade.aspx@gmail.com
License: MIT
Platform: UNKNOWN
Classifier: Programming Language :: Python :: 3.6
Classifier: Programming Language :: Python :: 3.7
Requires-Python: >=3.6
Provides-Extra: test
Requires-Dist: requests (>=2.10.0)
Requires-Dist: cachecontrol (>=0.12.0)
Requires-Dist: beautifulsoup4 (>=4.0.0)
Requires-Dist: urllib3 (>=1.18)
Requires-Dist: pytz (>=2017.2)
Provides-Extra: test
Requires-Dist: pytest (<3.7.0,>=3.5.0); extra == 'test'
Requires-Dist: pytest-flake8 (>=1.0.0); extra == 'test'
